PreLearn/src/rom.v
module rom(
	input	wire	ce,
	input	wire[5:0]	addr,
	
	output	reg[31:0]	inst
);

reg[31:0] rom[63:0];

always@(*) begin
	if(ce == 1'b0) begin
		inst <= 32'h0;
	end
	else begin
		inst <= rom[addr];
	end
end


endmodule

PreLearn/src/pc_reg.v
module pc_reg(

	input	wire	clk,
	input	wire	rst,

	output	reg[5:0]	pc,
	output	reg	ce

);


	always@(posedge clk) begin
		if(rst == 1'b1) begin
			ce <= 1'b0;
		end
		else begin
			ce <= 1'b1;
		end
	end

	always@(posedge clk) begin
		if(ce == 1'b0) begin
			pc<=6'h00;
		end 
		else begin 
			pc<=pc+1'b1;
		end
	end
endmodule

PreLearn/src/inst_fetch.v
module inst_fetch(
	input	wire	clk,
	input	wire	rst,

	output	wire[31:0]	inst_o
	
);

wire[5:0]	pc;
wire	rom_ce;


pc_reg pc_reg0(
	.clk(clk),
	.rst(rst),
	.pc(pc),
	.ce(rom_ce)
);

rom rom0(
	.ce(rom_ce),
	.addr(pc),
	.inst(inst_o)
);


endmodule

PreLearn/src/inst_fetch_tb.v
`timescale 1ns/1ps

module inst_fetch_tb;

reg	CLOCK;		//时钟信号
reg	rst;		//复位信号
wire[31:0]	inst;	//表示取出的指令



initial begin 
	$dumpfile("wave.vcd");
	$dumpvars(0,inst_fetch_tb);
end

//生成时钟信号
//每10ns翻转, 生成50MHz的时钟
initial begin
	CLOCK = 1'b0;
	forever #10 CLOCK = !CLOCK;
end

//生成复位信号
initial begin
	rst = 1'b1;
	#195 rst = 1'b0;
	#1000 $stop;
end

//实例化模块
inst_fetch inst_fetch0(
	.clk(CLOCK),
	.rst(rst),
	.inst_o(inst)
);

endmodule

PreLearn/src/wave.vcd
$date
	Wed Feb  1 18:09:16 2023
$end
$version
	Icarus Verilog
$end
$timescale
	1ps
$end
$scope module inst_fetch_tb $end
$var wire 32 ! inst [31:0] $end
$var reg 1 " CLOCK $end
$var reg 1 # rst $end
$scope module inst_fetch0 $end
$var wire 1 " clk $end
$var wire 1 # rst $end
$var wire 1 $ rom_ce $end
$var wire 6 % pc [5:0] $end
$var wire 32 & inst_o [31:0] $end
$scope module pc_reg0 $end
$var wire 1 " clk $end
$var wire 1 # rst $end
$var reg 1 $ ce $end
$var reg 6 ' pc [5:0] $end
$upscope $end
$scope module rom0 $end
$var wire 6 ( addr [5:0] $end
$var wire 1 $ ce $end
$var reg 32 ) inst [31:0] $end
$upscope $end
$upscope $end
$upscope $end
$enddefinitions $end
#0
$dumpvars
bx )
bx (
bx '
bx &
bx %
x$
1#
0"
bx !
$end
#10000
b0 !
b0 &
b0 )
0$
1"
#20000
0"
#30000
b0 %
b0 '
b0 (
1"
#40000
0"
#50000
1"
#60000
0"
#70000
1"
#80000
0"
#90000
1"
#100000
0"
#110000
1"
#120000
0"
#130000
1"
#140000
0"
#150000
1"
#160000
0"
#170000
1"
#180000
0"
#190000
1"
#195000
0#
#200000
0"
#210000
bx !
bx &
bx )
1$
1"
#220000
0"
#230000
b1 %
b1 '
b1 (
1"
#240000
0"
#250000
b10 %
b10 '
b10 (
1"
#260000
0"
#270000
b11 %
b11 '
b11 (
1"
#280000
0"
#290000
b100 %
b100 '
b100 (
1"
#300000
0"
#310000
b101 %
b101 '
b101 (
1"
#320000
0"
#330000
b110 %
b110 '
b110 (
1"
#340000
0"
#350000
b111 %
b111 '
b111 (
1"
#360000
0"
#370000
b1000 %
b1000 '
b1000 (
1"
#380000
0"
#390000
b1001 %
b1001 '
b1001 (
1"
#400000
0"
#410000
b1010 %
b1010 '
b1010 (
1"
#420000
0"
#430000
b1011 %
b1011 '
b1011 (
1"
#440000
0"
#450000
b1100 %
b1100 '
b1100 (
1"
#460000
0"
#470000
b1101 %
b1101 '
b1101 (
1"
#480000
0"
#490000
b1110 %
b1110 '
b1110 (
1"
#500000
0"
#510000
b1111 %
b1111 '
b1111 (
1"
#520000
0"
#530000
b10000 %
b10000 '
b10000 (
1"
#540000
0"
#550000
b10001 %
b10001 '
b10001 (
1"
#560000
0"
#570000
b10010 %
b10010 '
b10010 (
1"
#580000
0"
#590000
b10011 %
b10011 '
b10011 (
1"
#600000
0"
#610000
b10100 %
b10100 '
b10100 (
1"
#620000
0"
#630000
b10101 %
b10101 '
b10101 (
1"
#640000
0"
#650000
b10110 %
b10110 '
b10110 (
1"
#660000
0"
#670000
b10111 %
b10111 '
b10111 (
1"
#680000
0"
#690000
b11000 %
b11000 '
b11000 (
1"
#700000
0"
#710000
b11001 %
b11001 '
b11001 (
1"
#720000
0"
#730000
b11010 %
b11010 '
b11010 (
1"
#740000
0"
#750000
b11011 %
b11011 '
b11011 (
1"
#760000
0"
#770000
b11100 %
b11100 '
b11100 (
1"
#780000
0"
#790000
b11101 %
b11101 '
b11101 (
1"
#800000
0"
#810000
b11110 %
b11110 '
b11110 (
1"
#820000
0"
#830000
b11111 %
b11111 '
b11111 (
1"
#840000
0"
#850000
b100000 %
b100000 '
b100000 (
1"
#860000
0"
#870000
b100001 %
b100001 '
b100001 (
1"
#880000
0"
#890000
b100010 %
b100010 '
b100010 (
1"
#900000
0"
#910000
b100011 %
b100011 '
b100011 (
1"
#920000
0"
#930000
b100100 %
b100100 '
b100100 (
1"
#940000
0"
#950000
b100101 %
b100101 '
b100101 (
1"
#960000
0"
#970000
b100110 %
b100110 '
b100110 (
1"
#980000
0"
#990000
b100111 %
b100111 '
b100111 (
1"
#1000000
0"
#1010000
b101000 %
b101000 '
b101000 (
1"
#1020000
0"
#1030000
b101001 %
b101001 '
b101001 (
1"
#1040000
0"
#1050000
b101010 %
b101010 '
b101010 (
1"
#1060000
0"
#1070000
b101011 %
b101011 '
b101011 (
1"
#1080000
0"
#1090000
b101100 %
b101100 '
b101100 (
1"
#1100000
0"
#1110000
b101101 %
b101101 '
b101101 (
1"
#1120000
0"
#1130000
b101110 %
b101110 '
b101110 (
1"
#1140000
0"
#1150000
b101111 %
b101111 '
b101111 (
1"
#1160000
0"
#1170000
b110000 %
b110000 '
b110000 (
1"
#1180000
0"
#1190000
b110001 %
b110001 '
b110001 (
1"
